swh/model/__init__.py
swh/model/cli.py
swh/model/collections.py
swh/model/discovery.py
swh/model/exceptions.py
swh/model/from_disk.py
swh/model/git_objects.py
swh/model/hashutil.py
swh/model/hypothesis_strategies.py
swh/model/merkle.py
swh/model/model.py
swh/model/py.typed
swh/model/swhids.py
swh/model/toposort.py
swh/model/validators.py
swh/model/fields/__init__.py
swh/model/fields/compound.py
swh/model/fields/hashes.py
swh/model/fields/simple.py
swh/model/tests/__init__.py
swh/model/tests/conftest.py
swh/model/tests/generate_testdata.py
swh/model/tests/generate_testdata_from_disk.py
swh/model/tests/swh_model_data.py
swh/model/tests/test_cli.py
swh/model/tests/test_collections.py
swh/model/tests/test_discovery.py
swh/model/tests/test_from_disk.py
swh/model/tests/test_generate_testdata.py
swh/model/tests/test_hashutil.py
swh/model/tests/test_hypothesis_strategies.py
swh/model/tests/test_identifiers.py
swh/model/tests/test_merkle.py
swh/model/tests/test_model.py
swh/model/tests/test_swh_model_data.py
swh/model/tests/test_swhids.py
swh/model/tests/test_toposort.py
swh/model/tests/test_validators.py
swh/model/tests/data/dir-folders/sample-folder.tgz
swh/model/tests/data/repos/sample-repo.tgz
swh/model/tests/fields/__init__.py
swh/model/tests/fields/test_compound.py
swh/model/tests/fields/test_hashes.py
swh/model/tests/fields/test_simple.py
swh_model-8.4.1.dist-info/licenses/AUTHORS
swh_model-8.4.1.dist-info/licenses/LICENSE
swh_model-8.4.1.dist-info/METADATA
swh_model-8.4.1.dist-info/WHEEL
swh_model-8.4.1.dist-info/entry_points.txt
swh_model-8.4.1.dist-info/top_level.txt
swh_model-8.4.1.dist-info/RECORD
